bistring/__init__.py
bistring/_alignment.py
bistring/_bistr.py
bistring/_builder.py
bistring/_icu.py
bistring/_infer.py
bistring/_regex.py
bistring/_token.py
bistring/_typing.py
bistring/py.typed
bistring-0.5.0.dist-info/METADATA
bistring-0.5.0.dist-info/WHEEL
bistring-0.5.0.dist-info/top_level.txt
bistring-0.5.0.dist-info/RECORD
