Metadata-Version: 2.1
Name: bistring
Version: 0.5.0
Summary: Bidirectionally transformed strings
Home-page: https://github.com/microsoft/bistring
Author: Microsoft Research Montreal
Author-email: msrmtle@microsoft.com
License: MIT
Keywords: bistring string non-destructive
Platform: UNKNOWN
Classifier: Development Status :: 4 - Beta
Classifier: License :: OSI Approved :: MIT License
Classifier: Programming Language :: Python :: 3.7
Classifier: Programming Language :: Python :: 3.8
Classifier: Topic :: Text Processing :: General
Classifier: Typing :: Typed
Requires-Python: >=3.7
Requires-Dist: pyicu
Provides-Extra: dev
Requires-Dist: lxml ; extra == 'dev'
Requires-Dist: mypy ; extra == 'dev'
Requires-Dist: pytest ; extra == 'dev'
Requires-Dist: regex ; extra == 'dev'
